{
  "gerritStatsVersion": 1,
  "commits": [
    {
      "owner": {
        "name": "Andrew Macisaac",
        "email": "AMacisaac@sierrawireless.com",
        "username": "amacisaac"
      },
      "comments": [
        {
          "reviewer": {
            "name": "Andrew Macisaac",
            "email": "AMacisaac@sierrawireless.com",
            "username": "amacisaac"
          },
          "message": "Uploaded patch set 1.",
          "timestamp": 1556915336
        },
        {
          "reviewer": {
            "name": "Andrew Macisaac",
            "email": "AMacisaac@sierrawireless.com",
            "username": "amacisaac"
          },
          "message": "Set Work In Progress",
          "timestamp": 1557354282
        },
        {
          "reviewer": {
            "name": "Andrew Macisaac",
            "email": "AMacisaac@sierrawireless.com",
            "username": "amacisaac"
          },
          "message": "Patch Set 1:\n\nThis change is ready for review.",
          "timestamp": 1557431818
        },
        {
          "reviewer": {
            "name": "Andrew Macisaac",
            "email": "AMacisaac@sierrawireless.com",
            "username": "amacisaac"
          },
          "message": "Patch Set 2: Patch Set 1 was rebased",
          "timestamp": 1558558508
        },
        {
          "reviewer": {
            "name": "Andrew Macisaac",
            "email": "AMacisaac@sierrawireless.com",
            "username": "amacisaac"
          },
          "message": "Topic set to freertos-updates",
          "timestamp": 1558558602
        },
        {
          "reviewer": {
            "name": "Andrew Macisaac",
            "email": "AMacisaac@sierrawireless.com",
            "username": "amacisaac"
          },
          "message": "Abandoned\n\nWrong branch",
          "timestamp": 1558715070
        }
      ],
      "commitMessage": "Resolve some warnings about data type disparities\n\nGCC 8.2.1 with -Wall -Wextra -Werror complained about some type conversions.\n\nResolves: LE-12588\nChange-Id: Ic216f634f09a761aff16bb0157764dfc573f50b6\n",
      "subject": "Resolve some warnings about data type disparities",
      "project": "external/github/aws/amazon-freertos",
      "branch": "master",
      "createdOn": 1556915336,
      "url": "http://10.107.128.8:8081/c/external/github/aws/amazon-freertos/+/46026",
      "number": 46026,
      "lastUpdated": 1558715070,
      "allReviewers": [
        {
          "name": "Mohammad Ghasemi",
          "email": "MGhasemi@sierrawireless.com",
          "username": "mghasemi"
        },
        {
          "name": "Andrew Macisaac",
          "email": "AMacisaac@sierrawireless.com",
          "username": "amacisaac"
        },
        {
          "name": "Keith Dunwoody",
          "email": "kdunwoody@sierrawireless.com",
          "username": "kdunwoody"
        },
        {
          "name": "Jon Back",
          "email": "JBack@sierrawireless.com",
          "username": "jback"
        },
        {
          "name": "Tristan Pensel",
          "email": "tpensel@sierrawireless.com",
          "username": "tpensel"
        }
      ],
      "topic": "freertos-updates",
      "id": "Ic216f634f09a761aff16bb0157764dfc573f50b6",
      "open": false,
      "status": "ABANDONED",
      "patchSets": [
        {
          "number": 1,
          "sizeInsertions": 4,
          "ref": "refs/changes/26/46026/1",
          "uploader": {
            "name": "Andrew Macisaac",
            "email": "AMacisaac@sierrawireless.com",
            "username": "amacisaac"
          },
          "author": {
            "name": "Andrew MacIsaac",
            "email": "amacisaac@sierrawireless.com",
            "username": ""
          },
          "kind": "REWORK",
          "sizeDeletions": 4,
          "createdOn": 1556915336,
          "revision": "2c00d3bee374ca140517f02694ca79fdefc1322d",
          "parents": [
            "a2b064f67c8265d4a41ba4881c4b67f9a22af284"
          ]
        },
        {
          "number": 2,
          "sizeInsertions": 4,
          "ref": "refs/changes/26/46026/2",
          "uploader": {
            "name": "Andrew Macisaac",
            "email": "AMacisaac@sierrawireless.com",
            "username": "amacisaac"
          },
          "author": {
            "name": "Andrew MacIsaac",
            "email": "amacisaac@sierrawireless.com",
            "username": ""
          },
          "kind": "TRIVIAL_REBASE",
          "sizeDeletions": 4,
          "createdOn": 1558558508,
          "revision": "de30330189449d91b8ebccbdd2f1114acf86beb3",
          "parents": [
            "a1e88df84fece6fe3c030eb24218422990c607d6"
          ]
        }
      ]
    },
    {
      "owner": {
        "name": "Andrew Macisaac",
        "email": "AMacisaac@sierrawireless.com",
        "username": "amacisaac"
      },
      "comments": [
        {
          "reviewer": {
            "name": "Andrew Macisaac",
            "email": "AMacisaac@sierrawireless.com",
            "username": "amacisaac"
          },
          "message": "Uploaded patch set 1.",
          "timestamp": 1556915336
        },
        {
          "reviewer": {
            "name": "Andrew Macisaac",
            "email": "AMacisaac@sierrawireless.com",
            "username": "amacisaac"
          },
          "message": "Set Work In Progress",
          "timestamp": 1557354275
        },
        {
          "reviewer": {
            "name": "Andrew Macisaac",
            "email": "AMacisaac@sierrawireless.com",
            "username": "amacisaac"
          },
          "message": "Patch Set 1:\n\nThis change is ready for review.",
          "timestamp": 1557431851
        },
        {
          "reviewer": {
            "name": "Andrew Macisaac",
            "email": "AMacisaac@sierrawireless.com",
            "username": "amacisaac"
          },
          "message": "Patch Set 2: Patch Set 1 was rebased",
          "timestamp": 1558558548
        },
        {
          "reviewer": {
            "name": "Andrew Macisaac",
            "email": "AMacisaac@sierrawireless.com",
            "username": "amacisaac"
          },
          "message": "Topic set to freertos-updates",
          "timestamp": 1558558618
        },
        {
          "reviewer": {
            "name": "Andrew Macisaac",
            "email": "AMacisaac@sierrawireless.com",
            "username": "amacisaac"
          },
          "message": "Abandoned\n\nWrong branch",
          "timestamp": 1558715062
        }
      ],
      "commitMessage": "Allow overriding of sched_param structure\n\nSimilarly to some of the other pthread structures, this permits control\nover the definition of the sched_param structure.\n\nResolves: LE-12588\nChange-Id: I780bc12cd53a388e35d4d25b4ae78c1459a03a06\n",
      "subject": "Allow overriding of sched_param structure",
      "project": "external/github/aws/amazon-freertos",
      "branch": "master",
      "createdOn": 1556915336,
      "url": "http://10.107.128.8:8081/c/external/github/aws/amazon-freertos/+/46027",
      "number": 46027,
      "lastUpdated": 1558715062,
      "allReviewers": [
        {
          "name": "Mohammad Ghasemi",
          "email": "MGhasemi@sierrawireless.com",
          "username": "mghasemi"
        },
        {
          "name": "Andrew Macisaac",
          "email": "AMacisaac@sierrawireless.com",
          "username": "amacisaac"
        },
        {
          "name": "Keith Dunwoody",
          "email": "kdunwoody@sierrawireless.com",
          "username": "kdunwoody"
        },
        {
          "name": "Jon Back",
          "email": "JBack@sierrawireless.com",
          "username": "jback"
        },
        {
          "name": "Tristan Pensel",
          "email": "tpensel@sierrawireless.com",
          "username": "tpensel"
        },
        {
          "name": "CARMD-EV-GIT01_sa",
          "username": "carmd-ev-git01_sa"
        }
      ],
      "topic": "freertos-updates",
      "id": "I780bc12cd53a388e35d4d25b4ae78c1459a03a06",
      "open": false,
      "status": "ABANDONED",
      "patchSets": [
        {
          "number": 1,
          "sizeInsertions": 5,
          "ref": "refs/changes/27/46027/1",
          "uploader": {
            "name": "Andrew Macisaac",
            "email": "AMacisaac@sierrawireless.com",
            "username": "amacisaac"
          },
          "author": {
            "name": "Andrew MacIsaac",
            "email": "amacisaac@sierrawireless.com",
            "username": ""
          },
          "kind": "REWORK",
          "sizeDeletions": 0,
          "createdOn": 1556915336,
          "revision": "e7ebd7a4b9818427196fc293b7aab138c41ddf55",
          "parents": [
            "2c00d3bee374ca140517f02694ca79fdefc1322d"
          ]
        },
        {
          "number": 2,
          "sizeInsertions": 5,
          "ref": "refs/changes/27/46027/2",
          "uploader": {
            "name": "Andrew Macisaac",
            "email": "AMacisaac@sierrawireless.com",
            "username": "amacisaac"
          },
          "author": {
            "name": "Andrew MacIsaac",
            "email": "amacisaac@sierrawireless.com",
            "username": ""
          },
          "kind": "TRIVIAL_REBASE",
          "sizeDeletions": 0,
          "createdOn": 1558558548,
          "revision": "3dbeec6be5b5a4a95cc98c54eeb7f6200adb8c76",
          "parents": [
            "de30330189449d91b8ebccbdd2f1114acf86beb3"
          ]
        }
      ]
    },
    {
      "owner": {
        "name": "Andrew Macisaac",
        "email": "AMacisaac@sierrawireless.com",
        "username": "amacisaac"
      },
      "comments": [
        {
          "reviewer": {
            "name": "Andrew Macisaac",
            "email": "AMacisaac@sierrawireless.com",
            "username": "amacisaac"
          },
          "message": "Uploaded patch set 1.",
          "timestamp": 1556915336
        },
        {
          "reviewer": {
            "name": "Andrew Macisaac",
            "email": "AMacisaac@sierrawireless.com",
            "username": "amacisaac"
          },
          "message": "Uploaded patch set 2.",
          "timestamp": 1556915811
        },
        {
          "reviewer": {
            "name": "Andrew Macisaac",
            "email": "AMacisaac@sierrawireless.com",
            "username": "amacisaac"
          },
          "message": "Set Work In Progress",
          "timestamp": 1557354269
        },
        {
          "reviewer": {
            "name": "Andrew Macisaac",
            "email": "AMacisaac@sierrawireless.com",
            "username": "amacisaac"
          },
          "message": "Patch Set 2:\n\nThis change is ready for review.",
          "timestamp": 1557431871
        },
        {
          "reviewer": {
            "name": "Andrew Macisaac",
            "email": "AMacisaac@sierrawireless.com",
            "username": "amacisaac"
          },
          "message": "Patch Set 3: Patch Set 2 was rebased",
          "timestamp": 1558558559
        },
        {
          "reviewer": {
            "name": "Andrew Macisaac",
            "email": "AMacisaac@sierrawireless.com",
            "username": "amacisaac"
          },
          "message": "Topic set to freertos-updates",
          "timestamp": 1558558626
        },
        {
          "reviewer": {
            "name": "Andrew Macisaac",
            "email": "AMacisaac@sierrawireless.com",
            "username": "amacisaac"
          },
          "message": "Abandoned\n\nWrong branch",
          "timestamp": 1558715052
        }
      ],
      "commitMessage": "Add support for pthread_attr_setstack()\n\nThis allows created pthreads to be entirely allocated statically, by\ndelegating the allocation of stack and TCB space to the application\nusing the pthread API.\n\nResolves: LE-12588\nChange-Id: I99bf1e655ac5955c0e0e8e710b3aacfaab622b48\n",
      "subject": "Add support for pthread_attr_setstack()",
      "project": "external/github/aws/amazon-freertos",
      "branch": "master",
      "createdOn": 1556915336,
      "url": "http://10.107.128.8:8081/c/external/github/aws/amazon-freertos/+/46028",
      "number": 46028,
      "lastUpdated": 1558715052,
      "allReviewers": [
        {
          "name": "Mohammad Ghasemi",
          "email": "MGhasemi@sierrawireless.com",
          "username": "mghasemi"
        },
        {
          "name": "Andrew Macisaac",
          "email": "AMacisaac@sierrawireless.com",
          "username": "amacisaac"
        },
        {
          "name": "Keith Dunwoody",
          "email": "kdunwoody@sierrawireless.com",
          "username": "kdunwoody"
        },
        {
          "name": "Jon Back",
          "email": "JBack@sierrawireless.com",
          "username": "jback"
        },
        {
          "name": "Tristan Pensel",
          "email": "tpensel@sierrawireless.com",
          "username": "tpensel"
        }
      ],
      "topic": "freertos-updates",
      "id": "I99bf1e655ac5955c0e0e8e710b3aacfaab622b48",
      "open": false,
      "status": "ABANDONED",
      "patchSets": [
        {
          "number": 1,
          "sizeInsertions": 118,
          "ref": "refs/changes/28/46028/1",
          "uploader": {
            "name": "Andrew Macisaac",
            "email": "AMacisaac@sierrawireless.com",
            "username": "amacisaac"
          },
          "author": {
            "name": "Andrew MacIsaac",
            "email": "amacisaac@sierrawireless.com",
            "username": ""
          },
          "kind": "REWORK",
          "sizeDeletions": 19,
          "createdOn": 1556915336,
          "revision": "f7d374eba21e1722ecdf3a58cd58e3ab802567bf",
          "parents": [
            "e7ebd7a4b9818427196fc293b7aab138c41ddf55"
          ]
        },
        {
          "number": 2,
          "sizeInsertions": 140,
          "ref": "refs/changes/28/46028/2",
          "uploader": {
            "name": "Andrew Macisaac",
            "email": "AMacisaac@sierrawireless.com",
            "username": "amacisaac"
          },
          "author": {
            "name": "Andrew MacIsaac",
            "email": "amacisaac@sierrawireless.com",
            "username": ""
          },
          "kind": "REWORK",
          "sizeDeletions": 21,
          "createdOn": 1556915811,
          "revision": "553b8557a91b9a8a496c99f6d0573c8378e6e353",
          "parents": [
            "e7ebd7a4b9818427196fc293b7aab138c41ddf55"
          ]
        },
        {
          "number": 3,
          "sizeInsertions": 140,
          "ref": "refs/changes/28/46028/3",
          "uploader": {
            "name": "Andrew Macisaac",
            "email": "AMacisaac@sierrawireless.com",
            "username": "amacisaac"
          },
          "author": {
            "name": "Andrew MacIsaac",
            "email": "amacisaac@sierrawireless.com",
            "username": ""
          },
          "kind": "TRIVIAL_REBASE",
          "sizeDeletions": 21,
          "createdOn": 1558558559,
          "revision": "f1a64bcd750d6171124caa8c747a1221b9c00f0c",
          "parents": [
            "3dbeec6be5b5a4a95cc98c54eeb7f6200adb8c76"
          ]
        }
      ]
    },
    {
      "owner": {
        "name": "Andrew Macisaac",
        "email": "AMacisaac@sierrawireless.com",
        "username": "amacisaac"
      },
      "comments": [
        {
          "reviewer": {
            "name": "Andrew Macisaac",
            "email": "AMacisaac@sierrawireless.com",
            "username": "amacisaac"
          },
          "message": "Uploaded patch set 1.",
          "timestamp": 1556915811
        },
        {
          "reviewer": {
            "name": "Andrew Macisaac",
            "email": "AMacisaac@sierrawireless.com",
            "username": "amacisaac"
          },
          "message": "Set Work In Progress",
          "timestamp": 1557354263
        },
        {
          "reviewer": {
            "name": "Andrew Macisaac",
            "email": "AMacisaac@sierrawireless.com",
            "username": "amacisaac"
          },
          "message": "Patch Set 1:\n\nThis change is ready for review.",
          "timestamp": 1557431899
        },
        {
          "reviewer": {
            "name": "Andrew Macisaac",
            "email": "AMacisaac@sierrawireless.com",
            "username": "amacisaac"
          },
          "message": "Patch Set 2: Patch Set 1 was rebased",
          "timestamp": 1558558567
        },
        {
          "reviewer": {
            "name": "Andrew Macisaac",
            "email": "AMacisaac@sierrawireless.com",
            "username": "amacisaac"
          },
          "message": "Topic set to freertos-updates",
          "timestamp": 1558558633
        },
        {
          "reviewer": {
            "name": "Andrew Macisaac",
            "email": "AMacisaac@sierrawireless.com",
            "username": "amacisaac"
          },
          "message": "Abandoned\n\nWrong branch",
          "timestamp": 1558715045
        }
      ],
      "commitMessage": "Remove invalid mutex free call\n\nMutex was not allocated with pvPortMalloc() in this context.\n\nResolves: LE-12588\nChange-Id: Ib259732638a8251ace265bd9d652050227c21ca2\n",
      "subject": "Remove invalid mutex free call",
      "project": "external/github/aws/amazon-freertos",
      "branch": "master",
      "createdOn": 1556915811,
      "url": "http://10.107.128.8:8081/c/external/github/aws/amazon-freertos/+/46030",
      "number": 46030,
      "lastUpdated": 1558715045,
      "allReviewers": [
        {
          "name": "Mohammad Ghasemi",
          "email": "MGhasemi@sierrawireless.com",
          "username": "mghasemi"
        },
        {
          "name": "Andrew Macisaac",
          "email": "AMacisaac@sierrawireless.com",
          "username": "amacisaac"
        },
        {
          "name": "Keith Dunwoody",
          "email": "kdunwoody@sierrawireless.com",
          "username": "kdunwoody"
        },
        {
          "name": "Jon Back",
          "email": "JBack@sierrawireless.com",
          "username": "jback"
        },
        {
          "name": "Tristan Pensel",
          "email": "tpensel@sierrawireless.com",
          "username": "tpensel"
        }
      ],
      "topic": "freertos-updates",
      "id": "Ib259732638a8251ace265bd9d652050227c21ca2",
      "open": false,
      "status": "ABANDONED",
      "patchSets": [
        {
          "number": 1,
          "sizeInsertions": 0,
          "ref": "refs/changes/30/46030/1",
          "uploader": {
            "name": "Andrew Macisaac",
            "email": "AMacisaac@sierrawireless.com",
            "username": "amacisaac"
          },
          "author": {
            "name": "Andrew MacIsaac",
            "email": "amacisaac@sierrawireless.com",
            "username": ""
          },
          "kind": "REWORK",
          "sizeDeletions": 1,
          "createdOn": 1556915811,
          "revision": "ff505aa234abed51ea717d45d1c2950663edb13f",
          "parents": [
            "553b8557a91b9a8a496c99f6d0573c8378e6e353"
          ]
        },
        {
          "number": 2,
          "sizeInsertions": 0,
          "ref": "refs/changes/30/46030/2",
          "uploader": {
            "name": "Andrew Macisaac",
            "email": "AMacisaac@sierrawireless.com",
            "username": "amacisaac"
          },
          "author": {
            "name": "Andrew MacIsaac",
            "email": "amacisaac@sierrawireless.com",
            "username": ""
          },
          "kind": "TRIVIAL_REBASE",
          "sizeDeletions": 1,
          "createdOn": 1558558567,
          "revision": "ddeb1a1938a9c4c752dba9412326ccce003c8708",
          "parents": [
            "f1a64bcd750d6171124caa8c747a1221b9c00f0c"
          ]
        }
      ]
    }
  ],
  "gerritVersion": "3.3.-1"
}
