{
  "gerritStatsVersion": 1,
  "commits": [
    {
      "owner": {
        "name": "Chloe Strainge",
        "email": "CStrainge@sierrawireless.com",
        "username": "cstrainge"
      },
      "comments": [
        {
          "reviewer": {
            "name": "Chloe Strainge",
            "email": "CStrainge@sierrawireless.com",
            "username": "cstrainge"
          },
          "message": "Uploaded patch set 1.",
          "timestamp": 1502926852
        },
        {
          "reviewer": {
            "name": "CARMD-EV-LXCIM_sa",
            "email": "CARMD-EV-LXCIM_sa@sierrawireless.com",
            "username": "carmd-ev-lxcim_sa"
          },
          "message": "Patch Set 1: Quality-Check-2\n\nPlease check that the syntax of your ticket declaration(s) follows commit guidelines:\nhttps://confluence.sierrawireless.com/display/LEGATO/Write+Commit+Messages\n\n - Your commit should mention a least one ticket.",
          "timestamp": 1502926852
        },
        {
          "reviewer": {
            "name": "Chloe Strainge",
            "email": "CStrainge@sierrawireless.com",
            "username": "cstrainge"
          },
          "message": "Uploaded patch set 2: Commit message was updated.",
          "timestamp": 1502926915
        },
        {
          "reviewer": {
            "name": "Chloe Strainge",
            "email": "CStrainge@sierrawireless.com",
            "username": "cstrainge"
          },
          "message": "Uploaded patch set 3.",
          "timestamp": 1502927286
        },
        {
          "reviewer": {
            "name": "Jen Chitty",
            "email": "JChitty@sierrawireless.com",
            "username": "jchitty"
          },
          "message": "Patch Set 3: Code-Review-1\n\n(8 comments)",
          "timestamp": 1502990741
        },
        {
          "reviewer": {
            "name": "Chloe Strainge",
            "email": "CStrainge@sierrawireless.com",
            "username": "cstrainge"
          },
          "message": "Patch Set 3:\n\n(4 comments)",
          "timestamp": 1502994837
        },
        {
          "reviewer": {
            "name": "Chloe Strainge",
            "email": "CStrainge@sierrawireless.com",
            "username": "cstrainge"
          },
          "message": "Patch Set 3:\n\n(1 comment)",
          "timestamp": 1502994966
        },
        {
          "reviewer": {
            "name": "Apelete Seketeli",
            "email": "Aseketeli@sierrawireless.com",
            "username": "aseketeli"
          },
          "message": "Patch Set 3: Code-Review-1\n\n(1 comment)",
          "timestamp": 1503061607
        },
        {
          "reviewer": {
            "name": "Apelete Seketeli",
            "email": "Aseketeli@sierrawireless.com",
            "username": "aseketeli"
          },
          "message": "Patch Set 3:\n\n(1 comment)",
          "timestamp": 1503063070
        },
        {
          "reviewer": {
            "name": "Jen Chitty",
            "email": "JChitty@sierrawireless.com",
            "username": "jchitty"
          },
          "message": "Removed reviewer Jen Chitty with the following votes:\n\n* Code-Review-1 by Jen Chitty <jchitty@sierrawireless.com>\n",
          "timestamp": 1520886723
        },
        {
          "reviewer": {
            "name": "Chloe Strainge",
            "email": "CStrainge@sierrawireless.com",
            "username": "cstrainge"
          },
          "message": "Abandoned",
          "timestamp": 1521235794
        }
      ],
      "commitMessage": "Creating the initial make and config files.\n\nChange-Id: I72dc5c6d6186c886d7c252e9f5114ccb95bbc34b\nResolves: LE-7599\n",
      "subject": "Creating the initial make and config files.",
      "project": "toolchain/gnu-newlib-mips",
      "branch": "master",
      "createdOn": 1502926852,
      "url": "http://10.107.128.8:8081/c/toolchain/gnu-newlib-mips/+/17602",
      "number": 17602,
      "lastUpdated": 1521235794,
      "allReviewers": [
        {
          "name": "Apelete Seketeli",
          "email": "Aseketeli@sierrawireless.com",
          "username": "aseketeli"
        },
        {
          "name": "Chloe Strainge",
          "email": "CStrainge@sierrawireless.com",
          "username": "cstrainge"
        },
        {
          "name": "CARMD-EV-LXCIM_sa",
          "email": "CARMD-EV-LXCIM_sa@sierrawireless.com",
          "username": "carmd-ev-lxcim_sa"
        },
        {
          "name": "Kelly Murphy",
          "email": "kmurphy@sierrawireless.com",
          "username": "kmurphy"
        }
      ],
      "id": "I72dc5c6d6186c886d7c252e9f5114ccb95bbc34b",
      "open": false,
      "status": "ABANDONED",
      "patchSets": [
        {
          "number": 1,
          "sizeInsertions": 191,
          "ref": "refs/changes/02/17602/1",
          "uploader": {
            "name": "Chloe Strainge",
            "email": "CStrainge@sierrawireless.com",
            "username": "cstrainge"
          },
          "author": {
            "name": "Kelly Murphy",
            "email": "kmurphy@sierrawireless.com",
            "username": "kmurphy"
          },
          "kind": "REWORK",
          "sizeDeletions": 0,
          "approvals": [
            {
              "by": {
                "name": "CARMD-EV-LXCIM_sa",
                "email": "CARMD-EV-LXCIM_sa@sierrawireless.com",
                "username": "carmd-ev-lxcim_sa"
              },
              "grantedOn": 1502926852,
              "description": "Quality-Check",
              "type": "Quality-Check",
              "value": "-2"
            }
          ],
          "createdOn": 1502926852,
          "revision": "62adc3c862b6932ffff09f593ab9933b532c0a00",
          "parents": [
            "1d31dea13cf32137a60ab97b23ee734ea43a5a07"
          ]
        },
        {
          "number": 2,
          "sizeInsertions": 191,
          "ref": "refs/changes/02/17602/2",
          "uploader": {
            "name": "Chloe Strainge",
            "email": "CStrainge@sierrawireless.com",
            "username": "cstrainge"
          },
          "author": {
            "name": "Kelly Murphy",
            "email": "kmurphy@sierrawireless.com",
            "username": "kmurphy"
          },
          "kind": "NO_CODE_CHANGE",
          "sizeDeletions": 0,
          "createdOn": 1502926915,
          "revision": "3e7f339fc1e3c607dbd458e2a409d1c1422837f8",
          "parents": [
            "1d31dea13cf32137a60ab97b23ee734ea43a5a07"
          ]
        },
        {
          "number": 3,
          "sizeInsertions": 220,
          "ref": "refs/changes/02/17602/3",
          "comments": [
            {
              "file": "KConfig",
              "line": 17,
              "reviewer": {
                "name": "Jen Chitty",
                "email": "JChitty@sierrawireless.com",
                "username": "jchitty"
              },
              "message": "I'm thinking we should namespace these with a 'TOOLCHAIN_' prefix.\n\nAlso, this variable could be used for any toolchain, right?\n\n config TOOLCHAIN_SOURCE_BUILD\n\nI think any given top-level product should have only one toolchain, so we don't have to worry about naming conflicts between toolchains.\n\nCan we have this KConfig in the shared toolchain product and inherit from that by 'source'ing the shared toolchain KConfig in this KConfig?"
            },
            {
              "file": "KConfig",
              "line": 17,
              "reviewer": {
                "name": "Chloe Strainge",
                "email": "CStrainge@sierrawireless.com",
                "username": "cstrainge"
              },
              "message": "I'd like to keep them namespaced incase we go to multi-system products that need multiple different toolchains."
            },
            {
              "file": "KConfig",
              "line": 27,
              "reviewer": {
                "name": "Jen Chitty",
                "email": "JChitty@sierrawireless.com",
                "username": "jchitty"
              },
              "message": "TOOLCHAIN_INSTALL_DIR"
            },
            {
              "file": "KConfig",
              "line": 29,
              "reviewer": {
                "name": "Jen Chitty",
                "email": "JChitty@sierrawireless.com",
                "username": "jchitty"
              },
              "message": "The default should be local.  The product that uses the toolchain will run 'make -C toolchain' to build/install the toolchain before using it.\n\nBTW, the toolchain is not a Sierra Wireless toolchain.  It's a libre toolchain.  So, /opt/swi wouldn't be appropriate anyway."
            },
            {
              "file": "KConfig",
              "line": 29,
              "reviewer": {
                "name": "Chloe Strainge",
                "email": "CStrainge@sierrawireless.com",
                "username": "cstrainge"
              },
              "message": "Hmm...  Yeah.  My original thought was to make it more global so that it's easier to share among multiple products.\n\nMaybe I need to rethink this..."
            },
            {
              "file": "KConfig",
              "line": 29,
              "reviewer": {
                "name": "Apelete Seketeli",
                "email": "Aseketeli@sierrawireless.com",
                "username": "aseketeli"
              },
              "message": "FYI, for HL78 the extracted toolchain, the downloaded archives and the objects that are built lie in dedicated local directories under the product root directory (don't know if that's the best way to do it but it seems to be working fine so far):\n\naseketeli@FRILM-LX-ITE616:hl78.git$ tree -L 1\n.\n├── archive\n├── build\n├── default.config\n├── fetch\n├── hl78-map\n├── hl78-map.sdef\n├── KConfig\n├── legato-af\n├── Makefile\n└── toolchain\n\nOnly exception is the object files that result from the OpenRTOS build: these are built in place in hl78-map/build."
            },
            {
              "file": "KConfig",
              "line": 47,
              "reviewer": {
                "name": "Jen Chitty",
                "email": "JChitty@sierrawireless.com",
                "username": "jchitty"
              },
              "message": "TOOLCHAIN_SOURCE_DIR?"
            },
            {
              "file": "KConfig",
              "line": 47,
              "reviewer": {
                "name": "Chloe Strainge",
                "email": "CStrainge@sierrawireless.com",
                "username": "cstrainge"
              },
              "message": "It's intended to be the spot where the archives are downloaded, sources are extracted, and where the intermediate files live."
            },
            {
              "file": "KConfig",
              "line": 49,
              "reviewer": {
                "name": "Jen Chitty",
                "email": "JChitty@sierrawireless.com",
                "username": "jchitty"
              },
              "message": "Can't use environment variables here.\nThese definitions are put into Makefiles and C header files."
            },
            {
              "file": "KConfig",
              "line": 58,
              "reviewer": {
                "name": "Jen Chitty",
                "email": "JChitty@sierrawireless.com",
                "username": "jchitty"
              },
              "message": "Maybe we don't need this variable. It should be fine for the download/build to just always use $LEGATO_BUILD/toolchain.  If we need it to do something else later, we can change it later."
            },
            {
              "file": "KConfig",
              "line": 58,
              "reviewer": {
                "name": "Chloe Strainge",
                "email": "CStrainge@sierrawireless.com",
                "username": "cstrainge"
              },
              "message": "Hmm...  Yeah, that could work better."
            },
            {
              "file": "Makefile",
              "line": 11,
              "reviewer": {
                "name": "Jen Chitty",
                "email": "JChitty@sierrawireless.com",
                "username": "jchitty"
              },
              "message": "Why \"RTOS-Toolchain\"?  Seems to me that this is not needed.  Also, it seems like this toolchain could potentially be used for non-RTOS OSes too."
            },
            {
              "file": "Makefile",
              "line": 11,
              "reviewer": {
                "name": "Chloe Strainge",
                "email": "CStrainge@sierrawireless.com",
                "username": "cstrainge"
              },
              "message": "True.  Out of the box it's really intended for bare metal development.  (Which is why I didn't include C++ as that's it's own work to get going in this environment.)\n\nI'll need to think about the locations where the parts go some more."
            },
            {
              "file": "Makefile",
              "line": 125,
              "reviewer": {
                "name": "Apelete Seketeli",
                "email": "Aseketeli@sierrawireless.com",
                "username": "aseketeli"
              },
              "message": "The fetch goal that calls fetch/gnu-newlib-shared to pull in the shared scripts seems to be missing here."
            },
            {
              "file": "toolchain.sdef",
              "line": 1,
              "reviewer": {
                "name": "Jen Chitty",
                "email": "JChitty@sierrawireless.com",
                "username": "jchitty"
              },
              "message": "I don't think this .sdef is needed."
            }
          ],
          "uploader": {
            "name": "Chloe Strainge",
            "email": "CStrainge@sierrawireless.com",
            "username": "cstrainge"
          },
          "author": {
            "name": "Kelly Murphy",
            "email": "kmurphy@sierrawireless.com",
            "username": "kmurphy"
          },
          "kind": "REWORK",
          "sizeDeletions": 0,
          "approvals": [
            {
              "by": {
                "name": "Apelete Seketeli",
                "email": "Aseketeli@sierrawireless.com",
                "username": "aseketeli"
              },
              "grantedOn": 1503061607,
              "description": "Code-Review",
              "type": "Code-Review",
              "value": "-1"
            }
          ],
          "createdOn": 1502927286,
          "revision": "9fe290a39a5d3e44717e7065f6b8cddc15321924",
          "parents": [
            "1d31dea13cf32137a60ab97b23ee734ea43a5a07"
          ]
        }
      ]
    },
    {
      "owner": {
        "name": "Jen Chitty",
        "email": "JChitty@sierrawireless.com",
        "username": "jchitty"
      },
      "comments": [
        {
          "reviewer": {
            "name": "Jen Chitty",
            "email": "JChitty@sierrawireless.com",
            "username": "jchitty"
          },
          "message": "Uploaded patch set 1.",
          "timestamp": 1504221665
        },
        {
          "reviewer": {
            "name": "Jen Chitty",
            "email": "JChitty@sierrawireless.com",
            "username": "jchitty"
          },
          "message": "Topic set to LegatoRTOS-integration",
          "timestamp": 1504221872
        },
        {
          "reviewer": {
            "name": "Apelete Seketeli",
            "email": "Aseketeli@sierrawireless.com",
            "username": "aseketeli"
          },
          "message": "Patch Set 1: Code-Review+1",
          "timestamp": 1504620768
        },
        {
          "reviewer": {
            "name": "Jen Chitty",
            "email": "JChitty@sierrawireless.com",
            "username": "jchitty"
          },
          "message": "Patch Set 1: Verified+1 Code-Review+2",
          "timestamp": 1504906352
        },
        {
          "reviewer": {
            "name": "Jon Back",
            "email": "JBack@sierrawireless.com",
            "username": "jback"
          },
          "message": "Abandoned\n\nKeith's patch is based off Apelete's change.",
          "timestamp": 1505186397
        },
        {
          "reviewer": {
            "name": "Jen Chitty",
            "email": "JChitty@sierrawireless.com",
            "username": "jchitty"
          },
          "message": "Restored\n\nThis is not a duplicate.",
          "timestamp": 1505230611
        },
        {
          "reviewer": {
            "name": "Jen Chitty",
            "email": "JChitty@sierrawireless.com",
            "username": "jchitty"
          },
          "message": "Abandoned\n\nThe project went in another direction.",
          "timestamp": 1519342243
        }
      ],
      "commitMessage": "Fix integration issues\n\n- Stop exporting TARGET variable which means something else in\n  Legato AF build.\n- Tool chain is fetched next to LEGATO_ROOT, so paths can't\n  be relative to LEGATO_ROOT.  Removed paths.  Toolchain bin\n  directory can be added to PATH by the product Makefile.\n\nResolves: LE-7756\nChange-Id: Ib89b3c85a588471e4c8775730556930355d7bfdd\n",
      "subject": "Fix integration issues",
      "project": "toolchain/gnu-newlib-mips",
      "branch": "master",
      "createdOn": 1504221665,
      "url": "http://10.107.128.8:8081/c/toolchain/gnu-newlib-mips/+/18199",
      "number": 18199,
      "lastUpdated": 1519342243,
      "allReviewers": [
        {
          "name": "Jen Chitty",
          "email": "JChitty@sierrawireless.com",
          "username": "jchitty"
        },
        {
          "name": "Apelete Seketeli",
          "email": "Aseketeli@sierrawireless.com",
          "username": "aseketeli"
        },
        {
          "name": "Bertrand Roussel",
          "email": "broussel@sierrawireless.com",
          "username": "broussel"
        },
        {
          "name": "Jon Back",
          "email": "JBack@sierrawireless.com",
          "username": "jback"
        },
        {
          "name": "Keith Dunwoody",
          "email": "kdunwoody@sierrawireless.com",
          "username": "kdunwoody"
        },
        {
          "name": "Chloe Strainge",
          "email": "CStrainge@sierrawireless.com",
          "username": "cstrainge"
        },
        {
          "name": "CARMD-EV-LXCIM_sa",
          "email": "CARMD-EV-LXCIM_sa@sierrawireless.com",
          "username": "carmd-ev-lxcim_sa"
        }
      ],
      "topic": "LegatoRTOS-integration",
      "id": "Ib89b3c85a588471e4c8775730556930355d7bfdd",
      "open": false,
      "status": "ABANDONED",
      "patchSets": [
        {
          "number": 1,
          "sizeInsertions": 20,
          "ref": "refs/changes/99/18199/1",
          "uploader": {
            "name": "Jen Chitty",
            "email": "JChitty@sierrawireless.com",
            "username": "jchitty"
          },
          "author": {
            "name": "Jen Chitty",
            "email": "jchitty@sierrawireless.com",
            "username": ""
          },
          "kind": "REWORK",
          "sizeDeletions": 21,
          "approvals": [
            {
              "by": {
                "name": "Apelete Seketeli",
                "email": "Aseketeli@sierrawireless.com",
                "username": "aseketeli"
              },
              "grantedOn": 1504620768,
              "description": "Code-Review",
              "type": "Code-Review",
              "value": "1"
            },
            {
              "by": {
                "name": "Jen Chitty",
                "email": "JChitty@sierrawireless.com",
                "username": "jchitty"
              },
              "grantedOn": 1504906352,
              "description": "Verified",
              "type": "Verified",
              "value": "1"
            },
            {
              "by": {
                "name": "Jen Chitty",
                "email": "JChitty@sierrawireless.com",
                "username": "jchitty"
              },
              "grantedOn": 1504906352,
              "description": "Code-Review",
              "type": "Code-Review",
              "value": "2"
            }
          ],
          "createdOn": 1504221665,
          "revision": "6381c664ba817f9c5ee3bb85241bcf077ff9f266",
          "parents": [
            "cbf99088d513d727ac22dedbf1c9de1fd15e3e66"
          ]
        }
      ]
    },
    {
      "owner": {
        "name": "Chloe Strainge",
        "email": "CStrainge@sierrawireless.com",
        "username": "cstrainge"
      },
      "comments": [
        {
          "reviewer": {
            "name": "Chloe Strainge",
            "email": "CStrainge@sierrawireless.com",
            "username": "cstrainge"
          },
          "message": "Uploaded patch set 1.",
          "timestamp": 1503090503
        },
        {
          "reviewer": {
            "name": "Chloe Strainge",
            "email": "CStrainge@sierrawireless.com",
            "username": "cstrainge"
          },
          "message": "Uploaded patch set 2.",
          "timestamp": 1503431073
        },
        {
          "reviewer": {
            "name": "Jen Chitty",
            "email": "JChitty@sierrawireless.com",
            "username": "jchitty"
          },
          "message": "Patch Set 2: Verified+1 Code-Review+2",
          "timestamp": 1503431156
        },
        {
          "reviewer": {
            "name": "Jen Chitty",
            "email": "JChitty@sierrawireless.com",
            "username": "jchitty"
          },
          "message": "Change has been successfully merged by Jen Chitty",
          "timestamp": 1503431161
        }
      ],
      "commitMessage": "Importing the initial binary build of GCC.\n\nChange-Id: I7ca5ee43a91c869760181027b582a8fd4945c865\nResolves: LE-7599\n",
      "subject": "Importing the initial binary build of GCC.",
      "project": "toolchain/gnu-newlib-mips",
      "branch": "master",
      "createdOn": 1503090503,
      "url": "http://10.107.128.8:8081/c/toolchain/gnu-newlib-mips/+/17724",
      "number": 17724,
      "lastUpdated": 1503431161,
      "allReviewers": [
        {
          "name": "Jen Chitty",
          "email": "JChitty@sierrawireless.com",
          "username": "jchitty"
        },
        {
          "name": "CARMD-EV-LXCIM_sa",
          "email": "CARMD-EV-LXCIM_sa@sierrawireless.com",
          "username": "carmd-ev-lxcim_sa"
        },
        {
          "name": "Apelete Seketeli",
          "email": "Aseketeli@sierrawireless.com",
          "username": "aseketeli"
        },
        {
          "name": "Kelly Murphy",
          "email": "kmurphy@sierrawireless.com",
          "username": "kmurphy"
        }
      ],
      "id": "I7ca5ee43a91c869760181027b582a8fd4945c865",
      "open": false,
      "status": "MERGED",
      "patchSets": [
        {
          "number": 1,
          "sizeInsertions": 402368,
          "ref": "refs/changes/24/17724/1",
          "uploader": {
            "name": "Chloe Strainge",
            "email": "CStrainge@sierrawireless.com",
            "username": "cstrainge"
          },
          "author": {
            "name": "Kelly Murphy",
            "email": "kmurphy@sierrawireless.com",
            "username": "kmurphy"
          },
          "kind": "REWORK",
          "sizeDeletions": 0,
          "createdOn": 1503090503,
          "revision": "0f853e2af3ac1a0887b0a6bce363f3b7a6ee3eb0",
          "parents": [
            "1d31dea13cf32137a60ab97b23ee734ea43a5a07"
          ]
        },
        {
          "number": 2,
          "sizeInsertions": 402368,
          "ref": "refs/changes/24/17724/2",
          "uploader": {
            "name": "Chloe Strainge",
            "email": "CStrainge@sierrawireless.com",
            "username": "cstrainge"
          },
          "author": {
            "name": "Kelly Murphy",
            "email": "kmurphy@sierrawireless.com",
            "username": "kmurphy"
          },
          "kind": "REWORK",
          "sizeDeletions": 0,
          "approvals": [
            {
              "by": {
                "name": "Jen Chitty",
                "email": "JChitty@sierrawireless.com",
                "username": "jchitty"
              },
              "grantedOn": 1503431156,
              "description": "Verified",
              "type": "Verified",
              "value": "1"
            },
            {
              "by": {
                "name": "Jen Chitty",
                "email": "JChitty@sierrawireless.com",
                "username": "jchitty"
              },
              "grantedOn": 1503431156,
              "description": "Code-Review",
              "type": "Code-Review",
              "value": "2"
            },
            {
              "by": {
                "name": "Jen Chitty",
                "email": "JChitty@sierrawireless.com",
                "username": "jchitty"
              },
              "grantedOn": 1503431161,
              "type": "SUBM",
              "value": "1"
            }
          ],
          "createdOn": 1503431073,
          "revision": "cbf99088d513d727ac22dedbf1c9de1fd15e3e66",
          "parents": [
            "1d31dea13cf32137a60ab97b23ee734ea43a5a07"
          ]
        }
      ]
    }
  ],
  "gerritVersion": "3.3.-1"
}
